coda/__init__.py
hcgatewood_coda-1.0.0.dist-info/METADATA
hcgatewood_coda-1.0.0.dist-info/WHEEL
hcgatewood_coda-1.0.0.dist-info/RECORD
