Metadata-Version: 2.1
Name: hcgatewood_coda
Version: 1.0.0
Summary: Personal Lodash-style utility library
Author: Hunter Gatewood
Author-email: hgatewood@gmail.com
Requires-Python: >=3.10,<4.0
Classifier: Programming Language :: Python :: 3
Classifier: Programming Language :: Python :: 3.10
Classifier: Programming Language :: Python :: 3.11
Classifier: Programming Language :: Python :: 3.12
